zuicorn/__init__.py
zuicorn/wsgi.py
zuicorn-1.0.6.dist-info/METADATA
zuicorn-1.0.6.dist-info/WHEEL
zuicorn-1.0.6.dist-info/entry_points.txt
zuicorn-1.0.6.dist-info/top_level.txt
zuicorn-1.0.6.dist-info/RECORD
